doc2dict/__init__.py
doc2dict/convert_instructions_to_dict.py
doc2dict/dict2dict.py
doc2dict/mapping.py
doc2dict/html/__init__.py
doc2dict/html/convert_html_to_instructions.py
doc2dict/html/html2dict.py
doc2dict/html/mapping.py
doc2dict/html/visualize_dict.py
doc2dict/html/visualize_instructions.py
doc2dict/pdf/__init__.py
doc2dict/pdf/convert_pdf_to_instructions.py
doc2dict/pdf/mapping.py
doc2dict/pdf/pdf2dict.py
doc2dict/pdf/pdf_utils.py
doc2dict/pdf/utils.py
doc2dict/txt/__init__.py
doc2dict/txt/convert_txt_to_instructions.py
doc2dict/txt/txt2dict.py
doc2dict/utils/__init__.py
doc2dict/utils/format_dict.py
doc2dict/utils/strings.py
doc2dict/utils/utils.py
doc2dict/xml/__init__.py
doc2dict/xml/parser.py
doc2dict-0.5.0.dist-info/METADATA
doc2dict-0.5.0.dist-info/WHEEL
doc2dict-0.5.0.dist-info/top_level.txt
doc2dict-0.5.0.dist-info/RECORD
