Metadata-Version: 2.4
Name: doc2dict
Version: 0.5.0
Requires-Dist: selectolax
Requires-Dist: xmltodict
Requires-Dist: pypdfium2
Dynamic: requires-dist
